Metadata-Version: 2.1
Name: BiObjClassification
Version: 0.0.1
Summary: Bi-objective Lexicographical Classification
Author: Tiago Costa Soares, Pedro Augusto Mendes, Iago Augusto de Carvalho
Author-email: tiagocsoares22@gmail.com, pedroaugusto.mendes035@gmail.com, iago.carvalho@unifal-mg.edu.brZ
Keywords: classification,bi-objetive,lexicographical,ranking,csv
Classifier: Development Status :: 3 - Alpha
Classifier: Intended Audience :: Developers
Classifier: Intended Audience :: Science/Research
Classifier: Programming Language :: Python :: 3
Classifier: Operating System :: POSIX :: Linux
Classifier: Operating System :: Microsoft :: Windows
License-File: LICENSE
Requires-Dist: csvkit
